casparser/__init__.py
casparser/cli.py
casparser/enums.py
casparser/exceptions.py
casparser/types.py
casparser/analysis/__init__.py
casparser/analysis/gains.py
casparser/analysis/utils.py
casparser/parsers/__init__.py
casparser/parsers/mupdf.py
casparser/parsers/pdfminer.py
casparser/parsers/utils.py
casparser/process/__init__.py
casparser/process/cas_detailed.py
casparser/process/cas_summary.py
casparser/process/nsdl_statement.py
casparser/process/regex.py
casparser/process/utils.py
casparser-0.8.1.dist-info/METADATA
casparser-0.8.1.dist-info/WHEEL
casparser-0.8.1.dist-info/entry_points.txt
casparser-0.8.1.dist-info/licenses/LICENSE
casparser-0.8.1.dist-info/RECORD
