Metadata-Version: 2.4
Name: casparser
Version: 0.8.1
Summary: (Karvy/Kfintech/CAMS) Consolidated Account Statement (CAS) PDF parser
Project-URL: Homepage, https://github.com/codereverser/casparser
Author-email: Sandeep Somasekharan <codereverser@gmail.com>
License-Expression: MIT
License-File: LICENSE
Classifier: License :: OSI Approved :: MIT License
Classifier: Operating System :: OS Independent
Classifier: Programming Language :: Python :: 3.9
Classifier: Programming Language :: Python :: 3.10
Classifier: Programming Language :: Python :: 3.11
Classifier: Programming Language :: Python :: 3.12
Classifier: Programming Language :: Python :: 3.13
Requires-Python: ~=3.10
Requires-Dist: casparser-isin>=2025.2.28
Requires-Dist: click<9.0,>=7.0
Requires-Dist: colorama<0.5,>=0.4.6
Requires-Dist: pdfminer-six==20240706
Requires-Dist: pydantic<3,>=2.3.0
Requires-Dist: python-dateutil<3,>=2.8.2
Requires-Dist: rich<14,>=13.5.2
Provides-Extra: fast
Requires-Dist: pymupdf<1.25.0,>=1.24.0; extra == 'fast'
Provides-Extra: mupdf
Requires-Dist: pymupdf<1.25.0,>=1.24.0; extra == 'mupdf'
